README.md
setup.cfg
setup.py
DistributedMissForest/__init__.py
DistributedMissForest/impute.py
DistributedMissForest/job.py
DistributedMissForest/job_handler.py
DistributedMissForest/mf_local.py
DistributedMissForest/mf_slurm.py
DistributedMissForest/missforest.py
DistributedMissForest/randomforest.py
DistributedMissForest/util.py
DistributedMissForest.egg-info/PKG-INFO
DistributedMissForest.egg-info/SOURCES.txt
DistributedMissForest.egg-info/dependency_links.txt
DistributedMissForest.egg-info/requires.txt
DistributedMissForest.egg-info/top_level.txt