Metadata-Version: 2.1
Name: DistributedMissForest
Version: 1.4
Summary: MissForest in Python easy for Distribution on clusters
Home-page: https://github.com/fangzhouli/DistributedMissForest
Author: Fangzhou Li
Author-email: fzli0805@gmail.com
License: MIT
Download-URL: https://github.com/fangzhouli/DistributedMissForest/archive/v_01.tar.gz
Keywords: imputation,cluster computing
Platform: UNKNOWN
Classifier: Development Status :: 3 - Alpha
Classifier: Intended Audience :: Developers
Classifier: Topic :: Software Development :: Build Tools
Classifier: License :: OSI Approved :: MIT License
Classifier: Programming Language :: Python :: 3
